vyvodi/__init__.py
vyvodi/layers/__init__.py
vyvodi/layers/blocks.py
vyvodi/layers/dense_hierarchical.py
vyvodi-0.0.1.dist-info/LICENSE
vyvodi-0.0.1.dist-info/WHEEL
vyvodi-0.0.1.dist-info/METADATA
vyvodi-0.0.1.dist-info/RECORD
